[
  {
    "page": "https://www.concur.de/demo-anfragen",
    "statusCode": 200,
    "redirectUrls": []
  },
  {
    "page": "https://www.concursolutions.com/?lang=de",
    "statusCode": 200,
    "redirectUrls": [
      "https://www.concursolutions.com/nui/signin?lang=de"
    ]
  },
  {
    "page": "https://www.concur.de/reisekostenabrechnung",
    "statusCode": 200,
    "redirectUrls": []
  },
  {
    "page": "https://www.concur.de/budget-management",
    "statusCode": 200,
    "redirectUrls": []
  },
  {
    "page": "https://www.concur.de/fahrtkostenabrechnung",
    "statusCode": 200,
    "redirectUrls": []
  },
  {
    "page": "https://www.concur.de/rueckerstattung",
    "statusCode": 200,
    "redirectUrls": []
  },
  {
    "page": "https://www.concur.de/mehrwertsteuerrueckerstattung",
    "statusCode": 200,
    "redirectUrls": []
  },
  {
    "page": "https://www.concur.de/reisekostenaudit",
    "statusCode": 200,
    "redirectUrls": []
  },
  {
    "page": "https://www.concur.de/reisekosten-app",
    "statusCode": 200,
    "redirectUrls": []
  },
  {
    "page": "https://www.concur.de/digitale-belegerfassung",
    "statusCode": 200,
    "redirectUrls": []
  },
  {
    "page": "https://www.concur.de/app-center",
    "statusCode": 200,
    "redirectUrls": []
  },
  {
    "page": "https://www.concur.de/reisekostenprozess",
    "statusCode": 200,
    "redirectUrls": []
  },
  {
    "page": "https://www.concur.de/reiseantrag",
    "statusCode": 200,
    "redirectUrls": []
  },
  {
    "page": "https://www.concur.de/reisemanagement",
    "statusCode": 200,
    "redirectUrls": []
  },
  {
    "page": "https://www.concur.de/budget-management",
    "statusCode": 200,
    "redirectUrls": []
  },
  {
    "page": "https://www.concur.de/reisekosten-app",
    "statusCode": 200,
    "redirectUrls": []
  },
  {
    "page": "https://www.concur.de/triplink",
    "statusCode": 200,
    "redirectUrls": []
  },
  {
    "page": "https://www.concur.de/app-center",
    "statusCode": 200,
    "redirectUrls": []
  },
  {
    "page": "https://www.concur.de/reisekostenprozess",
    "statusCode": 200,
    "redirectUrls": []
  },
  {
    "page": "https://www.concur.de/plattform",
    "statusCode": 200,
    "redirectUrls": []
  },
  {
    "page": "https://www.concur.de/reisekostenprozess",
    "statusCode": 200,
    "redirectUrls": []
  },
  {
    "page": "https://www.concur.de/system-integration",
    "statusCode": 200,
    "redirectUrls": []
  },
  {
    "page": "https://www.concur.de/sap-integration",
    "statusCode": 200,
    "redirectUrls": []
  },
  {
    "page": "https://www.concur.de/cloud",
    "statusCode": 200,
    "redirectUrls": []
  },
  {
    "page": "https://www.concur.de/ctrip",
    "statusCode": 200,
    "redirectUrls": []
  },
  {
    "page": "https://www.concur.de/budget-management",
    "statusCode": 200,
    "redirectUrls": []
  },
  {
    "page": "https://www.concur.de/reporting",
    "statusCode": 200,
    "redirectUrls": []
  },
  {
    "page": "https://www.concur.de/reporting-beratung",
    "statusCode": 200,
    "redirectUrls": []
  },
  {
    "page": "https://www.concur.de/tmc-loesungen",
    "statusCode": 200,
    "redirectUrls": []
  },
  {
    "page": "https://www.concur.de/tmc-loesungen/compleat",
    "statusCode": 200,
    "redirectUrls": []
  },
  {
    "page": "https://www.concur.de/tmc-loesungen/task-manager",
    "statusCode": 200,
    "redirectUrls": []
  },
  {
    "page": "https://www.concur.de/tmc-loesungen/trip-approval",
    "statusCode": 200,
    "redirectUrls": []
  },
  {
    "page": "https://www.concur.de/tmc-loesungen/travpay",
    "statusCode": 200,
    "redirectUrls": []
  },
  {
    "page": "https://www.concur.de/tmc-loesungen/tss",
    "statusCode": 200,
    "redirectUrls": []
  },
  {
    "page": "https://www.concur.de/endnutzer-support",
    "statusCode": 200,
    "redirectUrls": []
  },
  {
    "page": "https://www.concur.de/admin-beratung",
    "statusCode": 200,
    "redirectUrls": []
  },
  {
    "page": "https://www.concur.de/erweiterter-support",
    "statusCode": 200,
    "redirectUrls": []
  },
  {
    "page": "https://www.concur.de/produkte",
    "statusCode": 200,
    "redirectUrls": []
  },
  {
    "page": "https://www.concur.de/demo-anfragen",
    "statusCode": 200,
    "redirectUrls": []
  },
  {
    "page": "https://www.concur.de/rentabilitaet",
    "statusCode": 200,
    "redirectUrls": []
  },
  {
    "page": "https://www.concur.de/compliance",
    "statusCode": 200,
    "redirectUrls": []
  },
  {
    "page": "https://www.concur.de/transparenz",
    "statusCode": 200,
    "redirectUrls": []
  },
  {
    "page": "https://www.concur.de/employee-experience",
    "statusCode": 200,
    "redirectUrls": []
  },
  {
    "page": "https://www.concur.de/nachhaltigkeit",
    "statusCode": 200,
    "redirectUrls": []
  },
  {
    "page": "https://www.concur.de/automobil-industrie",
    "statusCode": 200,
    "redirectUrls": []
  },
  {
    "page": "https://www.concur.de/einzelhandel",
    "statusCode": 200,
    "redirectUrls": []
  },
  {
    "page": "https://www.concur.de/finanzsektor",
    "statusCode": 200,
    "redirectUrls": []
  },
  {
    "page": "https://www.concur.de/verarbeitendes-gewerbe",
    "statusCode": 200,
    "redirectUrls": []
  },
  {
    "page": "https://www.concur.de/pharma",
    "statusCode": 200,
    "redirectUrls": []
  },
  {
    "page": "https://www.concur.de/versorgungsunternehmen",
    "statusCode": 200,
    "redirectUrls": []
  },
  {
    "page": "https://www.concur.de/oeffentlicher-dienst",
    "statusCode": 200,
    "redirectUrls": []
  },
  {
    "page": "https://www.concur.de/finanzentscheider",
    "statusCode": 200,
    "redirectUrls": []
  },
  {
    "page": "https://www.concur.de/travel-manager",
    "statusCode": 200,
    "redirectUrls": []
  },
  {
    "page": "https://www.concur.de/it",
    "statusCode": 200,
    "redirectUrls": []
  },
  {
    "page": "https://www.concur.de/hr-manager",
    "statusCode": 200,
    "redirectUrls": []
  },
  {
    "page": "https://www.concur.de/reisende",
    "statusCode": 200,
    "redirectUrls": []
  },
  {
    "page": "https://www.concur.de/mittelstand",
    "statusCode": 200,
    "redirectUrls": []
  },
  {
    "page": "https://www.concur.de/kunden",
    "statusCode": 200,
    "redirectUrls": []
  },
  {
    "page": "https://www.concur.de/intelligentes-unternehmen",
    "statusCode": 200,
    "redirectUrls": []
  },
  {
    "page": "https://www.concur.de/kontakt",
    "statusCode": 200,
    "redirectUrls": []
  },
  {
    "page": "https://www.concur.de/veranstaltungen",
    "statusCode": 200,
    "redirectUrls": []
  },
  {
    "page": "https://www.concur.de/resource-center/all",
    "statusCode": 200,
    "redirectUrls": []
  },
  {
    "page": "https://www.concur.de/casestudy",
    "statusCode": 200,
    "redirectUrls": []
  },
  {
    "page": "https://www.concur.de/newsroom",
    "statusCode": 200,
    "redirectUrls": []
  },
  {
    "page": "https://www.concur.de/veranstaltungen",
    "statusCode": 200,
    "redirectUrls": []
  },
  {
    "page": "https://www.concur.de/news-service",
    "statusCode": 200,
    "redirectUrls": []
  },
  {
    "page": "https://www.concur.de/app-center",
    "statusCode": 200,
    "redirectUrls": []
  },
  {
    "page": "https://www.concur.de/faq",
    "statusCode": 200,
    "redirectUrls": []
  },
  {
    "page": "https://www.concur.de/self-guided-demo-expense-de-de",
    "statusCode": 200,
    "redirectUrls": []
  },
  {
    "page": "https://www.concur.de/ueber-sap-concur",
    "statusCode": 200,
    "redirectUrls": []
  },
  {
    "page": "https://www.concur.de/plattform",
    "statusCode": 200,
    "redirectUrls": []
  },
  {
    "page": "https://www.concur.de/partner-netzwerk",
    "statusCode": 200,
    "redirectUrls": []
  },
  {
    "page": "https://www.concur.de/rezensionen",
    "statusCode": 200,
    "redirectUrls": []
  },
  {
    "page": "https://www.concur.de/karriere",
    "statusCode": 200,
    "redirectUrls": []
  },
  {
    "page": "https://www.concur.de/kontakt/standorte",
    "statusCode": 200,
    "redirectUrls": []
  },
  {
    "page": "https://www.concur.de/kontakt/ansprechpartner",
    "statusCode": 200,
    "redirectUrls": []
  },
  {
    "page": "https://www.concur.de/datenschutz",
    "statusCode": 200,
    "redirectUrls": []
  },
  {
    "page": "https://www.concur.de/impressum",
    "statusCode": 200,
    "redirectUrls": []
  },
  {
    "page": "https://www.concur.de/kontakt/support",
    "statusCode": 200,
    "redirectUrls": []
  },
  {
    "page": "https://www.concur.de/kontakt",
    "statusCode": 200,
    "redirectUrls": []
  },
  {
    "page": "http://open.concur.com/",
    "statusCode": 200,
    "redirectUrls": [
      "https://open.concur.com/"
    ]
  },
  {
    "page": "https://www.concur.de/kontakt",
    "statusCode": 200,
    "redirectUrls": []
  },
  {
    "page": "https://www.concur.de/support",
    "statusCode": 200,
    "redirectUrls": [
      "https://www.concur.de/kontakt/support"
    ]
  }
]